textrl/__init__.py
textrl/actor.py
textrl/dump.py
textrl/environment.py
textrl/evaluator.py
textrl/trainer.py
textrl-0.2.22.dist-info/LICENSE
textrl-0.2.22.dist-info/METADATA
textrl-0.2.22.dist-info/WHEEL
textrl-0.2.22.dist-info/entry_points.txt
textrl-0.2.22.dist-info/top_level.txt
textrl-0.2.22.dist-info/RECORD
