Metadata-Version: 2.1
Name: textrl
Version: 0.2.22
Summary: TextRL - use reinforcement learning to adjust text generation results.
Home-page: https://github.com/voidful/TextRL
Author: Voidful
Author-email: voidful.stack@gmail.com
License: Apache
Keywords: transformer huggingface nlp generation reinforcement learning deep learning
Platform: UNKNOWN
Classifier: Development Status :: 4 - Beta
Classifier: Intended Audience :: Science/Research
Classifier: Topic :: Scientific/Engineering :: Artificial Intelligence
Classifier: License :: OSI Approved :: Apache Software License
Classifier: Programming Language :: Python :: 3.6
Requires-Python: >=3.5.0
License-File: LICENSE
Requires-Dist: gym
Requires-Dist: transformers
